lupa-stubs/METADATA.toml
lupa-stubs/__init__.pyi
lupa-stubs/lua51.pyi
lupa-stubs/lua52.pyi
lupa-stubs/lua53.pyi
lupa-stubs/lua54.pyi
lupa-stubs/luajit20.pyi
lupa-stubs/luajit21.pyi
lupa-stubs/py.typed
lupa-stubs/version.pyi
types_lupa-2.5.0.20250915.dist-info/licenses/LICENSE
types_lupa-2.5.0.20250915.dist-info/METADATA
types_lupa-2.5.0.20250915.dist-info/WHEEL
types_lupa-2.5.0.20250915.dist-info/top_level.txt
types_lupa-2.5.0.20250915.dist-info/RECORD
